thermo_stability/__init__.py
thermo_stability/config.py
thermo_stability/feature.py
thermo_stability/mpi_creds.py
thermo_stability/processing.py
thermo_stability/utils.py
thermo_stability-0.0.6.dist-info/METADATA
thermo_stability-0.0.6.dist-info/WHEEL
thermo_stability-0.0.6.dist-info/licenses/LICENSE.txt
thermo_stability-0.0.6.dist-info/RECORD
