Metadata-Version: 2.4
Name: thermo_stability
Version: 0.0.6
Summary: Thermodynamic stability of chemical compound using ML methods.
Author-email: Sara Nabili <srnabili@gmail.com>
License-File: LICENSE.txt
Classifier: License :: OSI Approved :: MIT License
Classifier: Operating System :: OS Independent
Classifier: Programming Language :: Python :: 3
Requires-Python: >=3.10.17
Requires-Dist: argparse
Requires-Dist: joblib
Requires-Dist: matplotlib==3.8.2
Requires-Dist: mp-api==0.45.5
Requires-Dist: numpy==1.26.4
Requires-Dist: pandas
Requires-Dist: psutil
Requires-Dist: pymatgen
Requires-Dist: scikeras==0.12.0
Requires-Dist: scikit-learn==1.3.2
Requires-Dist: tensorflow-macos==2.15.0
Requires-Dist: tensorflow-metal==1.1.0
Requires-Dist: tqdm
Requires-Dist: xgboost==2.0.3
